dbdata.py
scream.py
scream_api_dbl-0.1.0.dist-info/METADATA
scream_api_dbl-0.1.0.dist-info/WHEEL
scream_api_dbl-0.1.0.dist-info/top_level.txt
scream_api_dbl-0.1.0.dist-info/RECORD
