Metadata-Version: 2.4
Name: scream.api.dbl
Version: 0.1.0
Summary: DBLPS tingz
Author: mindsetdbl111
Author-email: 
Classifier: Programming Language :: Python :: 3
Classifier: License :: OSI Approved :: MIT License
Classifier: Operating System :: OS Independent
Requires-Python: >=3.6
Dynamic: author
Dynamic: classifier
Dynamic: requires-python
Dynamic: summary
